gino_tornado.py
gino_tornado-0.1.0.dist-info/entry_points.txt
gino_tornado-0.1.0.dist-info/LICENSE
gino_tornado-0.1.0.dist-info/WHEEL
gino_tornado-0.1.0.dist-info/METADATA
gino_tornado-0.1.0.dist-info/RECORD
